xontrib/xpg.xsh
xpg/__init__.py
xpg/conn.py
xpg/xtable.py
xpg/xtplot.py
xpg-0.1.0.dist-info/LICENSE.txt
xpg-0.1.0.dist-info/METADATA
xpg-0.1.0.dist-info/WHEEL
xpg-0.1.0.dist-info/top_level.txt
xpg-0.1.0.dist-info/RECORD
