Metadata-Version: 2.1
Name: xpg
Version: 0.1.0
Summary: xonsh python for pg
Home-page: https://github.com/fengttt/xsh/py/xpg
Author: Feng Tian
Author-email: fengttt@gmail.com
License: UNKNOWN
Keywords: xonsh postgresql
Platform: UNKNOWN
Classifier: Development Status :: 4 - Beta
Classifier: Intended Audience :: Developers
Classifier: Topic :: Software Development :: Build Tools
Classifier: License :: OSI Approved :: MIT License
Classifier: Programming Language :: Python :: 3
Requires-Dist: psycopg2
Requires-Dist: graphviz
Requires-Dist: tabulate
